vsdm/__init__.py
vsdm/adaptive.py
vsdm/analytic.py
vsdm/basis.py
vsdm/gaussians.py
vsdm/haar.py
vsdm/matrixcalc.py
vsdm/portfolio.py
vsdm/projection.py
vsdm/ratecalc.py
vsdm/units.py
vsdm/utilities.py
vsdm/wigner.py
vsdm-0.4.4.dist-info/LICENSE
vsdm-0.4.4.dist-info/METADATA
vsdm-0.4.4.dist-info/WHEEL
vsdm-0.4.4.dist-info/top_level.txt
vsdm-0.4.4.dist-info/RECORD
