Metadata-Version: 2.2
Name: vsdm
Version: 0.4.4
Summary: Vector space integration for dark matter direct detection
Author-email: "Ben G. Lillard" <blillard@uoregon.edu>
Project-URL: Homepage, https://github.com/blillard/vsdm
Project-URL: Source, https://github.com/blillard/vsdm/
Project-URL: Documentation, https://github.com/blillard/vsdm/blob/main/README.md
Classifier: Intended Audience :: Science/Research
Classifier: Topic :: Scientific/Engineering :: Physics
Classifier: Programming Language :: Python :: 3
Requires-Python: >=3.7
License-File: LICENSE
Requires-Dist: numba
Requires-Dist: scipy
Requires-Dist: vegas
Requires-Dist: h5py
Requires-Dist: spherical
Requires-Dist: quaternionic
